README.rst
setup.py
kumparan/__init__.py
kumparan/service_account.py
kumparan/stackdriver.py
kumparan/utils.py
kumparan.egg-info/PKG-INFO
kumparan.egg-info/SOURCES.txt
kumparan.egg-info/dependency_links.txt
kumparan.egg-info/requires.txt
kumparan.egg-info/top_level.txt