Metadata-Version: 1.1
Name: kumparan
Version: 0.0.4
Summary: Kumparan's Python Package
Home-page: https://github.com/kumparan/kumparan.py
Author: Bayu Aldi Yansyah
Author-email: bayualdiyansyah@gmail.com
License: BSD 3-Clause License
Platform: UNKNOWN
Classifier: License :: OSI Approved :: BSD License
Classifier: Programming Language :: Python :: 3.6
